jwt_kms/__init__.py
jwt_kms/jwa.py
jwt_kms/jwk.py
jwt_kms/jws.py
jwt_kms-0.1.4.dist-info/LICENSE
jwt_kms-0.1.4.dist-info/METADATA
jwt_kms-0.1.4.dist-info/WHEEL
jwt_kms-0.1.4.dist-info/entry_points.txt
jwt_kms-0.1.4.dist-info/RECORD
