Metadata-Version: 2.1
Name: jwt-kms
Version: 0.1.4
Summary: Library to offload some JWT crypto operations to KMS
Home-page: https://github.com/jmtapio/python-jwt-kms
License: MIT
Author: Juha-Matti Tapio
Author-email: jmtapio@verkkotelakka.net
Requires-Python: >=3.9.2
Classifier: License :: OSI Approved :: MIT License
Classifier: Programming Language :: Python :: 3
Classifier: Programming Language :: Python :: 3.10
Classifier: Programming Language :: Python :: 3.11
Classifier: Programming Language :: Python :: 3.12
Requires-Dist: cryptography (>=44.0.0)
Project-URL: Repository, https://github.com/jmtapio/python-jwt-kms
